verilog/project.v
module TemperatureLightPowerController (
    input wire clk,
    input wire rst,
    input wire [7:0] temperature_sensor,  // 8-bit temperature sensor data
    input wire [7:0] light_sensor,        // 8-bit light sensor data
    input wire [8:0] power_monitor,       // 9-bit power usage monitor (0-511 units)
    output wire heater,                   // Heater control signal
    output wire cooler,                   // Cooler control signal
    output wire light,                    // Light control signal
    output wire alarm                     // Alarm control signal
);

// Define some constants for control thresholds
parameter TEMPERATURE_THRESHOLD = 8'b00100000;  // Example temperature threshold (adjust as needed)
parameter LIGHT_THRESHOLD = 8'b00110000;        // Example light threshold (48)
parameter POWER_THRESHOLD = 9'b010100000;       // Example power threshold (160 units)

// Registers for control logic
reg heater_reg, cooler_reg, light_reg, alarm_reg;

always @(posedge clk or posedge rst) begin
    if (rst) begin
        heater_reg <= 1'b0;
        cooler_reg <= 1'b0;
        light_reg <= 1'b0;
        alarm_reg <= 1'b0;
    end else begin
        // Temperature control logic
        if (temperature_sensor > TEMPERATURE_THRESHOLD) begin
            cooler_reg <= 1'b1;
            heater_reg <= 1'b0;
        end else if (temperature_sensor < TEMPERATURE_THRESHOLD) begin
            cooler_reg <= 1'b0;
            heater_reg <= 1'b1;
        end else begin
            cooler_reg <= 1'b0;
            heater_reg <= 1'b0;
        end

        // Light control logic
        if (light_sensor < LIGHT_THRESHOLD) begin
            light_reg <= 1'b1;
        end else begin
            light_reg <= 1'b0;
        end

        // Power usage alarm logic
        if (power_monitor > POWER_THRESHOLD) begin
            alarm_reg <= 1'b1;
        end else begin
            alarm_reg <= 1'b0;
        end
    end
end

assign heater = heater_reg;
assign cooler = cooler_reg;
assign light = light_reg;
assign alarm = alarm_reg;

endmodule

verilog/project_tb.v
module TemperatureLightPowerController_tb;

reg clk;
reg rst;
reg [7:0] temperature_sensor;
reg [7:0] light_sensor;
reg [8:0] power_monitor;
wire heater;
wire cooler;
wire light;
wire alarm;

// Instantiate the controller module
TemperatureLightPowerController uut (
    .clk(clk),
    .rst(rst),
    .temperature_sensor(temperature_sensor),
    .light_sensor(light_sensor),
    .power_monitor(power_monitor),
    .heater(heater),
    .cooler(cooler),
    .light(light),
    .alarm(alarm)
);

// Clock generation
always begin
    #5 clk = ~clk;
end

initial begin
    clk = 0;
    rst = 1;
    temperature_sensor = 8'b00000000;
    light_sensor = 8'b00000000;
    power_monitor = 9'b000000000;
    #10 rst = 0;

    // Monitor the control signals
    $monitor("Time=%0t: Temp=%d Light=%d Power=%d Heater=%b Cooler=%b Light=%b Alarm=%b",
             $time, temperature_sensor, light_sensor, power_monitor, heater, cooler, light, alarm);

    // Simulate temperature, light, and power data changes
    #10 temperature_sensor = 8'b01010101; // Example: 85 (adjust as needed)
    #10 light_sensor = 8'b00110011;       // Example: 51 (adjust as needed)
    #10 power_monitor = 9'b101000001;    // Example: 321 (adjust as needed)

    // Add more test scenarios as needed

    #1000 $finish;
end

endmodule

verilog/project.vcd
$date
	Sun Nov 05 12:53:49 2023
$end
$version
	Icarus Verilog
$end
$timescale
	1s
$end
$scope module TemperatureLightPowerController_tb $end
$var wire 1 ! light $end
$var wire 1 " heater $end
$var wire 1 # cooler $end
$var wire 1 $ alarm $end
$var reg 1 % clk $end
$var reg 8 & light_sensor [7:0] $end
$var reg 9 ' power_monitor [8:0] $end
$var reg 1 ( rst $end
$var reg 8 ) temperature_sensor [7:0] $end
$scope module uut $end
$var wire 1 $ alarm $end
$var wire 1 % clk $end
$var wire 1 # cooler $end
$var wire 1 " heater $end
$var wire 1 ! light $end
$var wire 8 * light_sensor [7:0] $end
$var wire 9 + power_monitor [8:0] $end
$var wire 1 ( rst $end
$var wire 8 , temperature_sensor [7:0] $end
$var parameter 8 - LIGHT_THRESHOLD $end
$var parameter 9 . POWER_THRESHOLD $end
$var parameter 8 / TEMPERATURE_THRESHOLD $end
$var reg 1 0 alarm_reg $end
$var reg 1 1 cooler_reg $end
$var reg 1 2 heater_reg $end
$var reg 1 3 light_reg $end
$upscope $end
$upscope $end
$enddefinitions $end
$comment Show the parameter values. $end
$dumpall
b100000 /
b10100000 .
b110000 -
$end
#0
$dumpvars
03
02
01
00
b0 ,
b0 +
b0 *
b0 )
1(
b0 '
b0 &
0%
0$
0#
0"
0!
$end
#5
1%
#10
0%
0(
#15
1!
13
1"
12
1%
#20
0%
b1010101 )
b1010101 ,
#25
0"
02
1#
11
1%
#30
0%
b110011 &
b110011 *
#35
0!
03
1%
#40
0%
b101000001 '
b101000001 +
#45
1$
10
1%
